gcp_utility-2.0.5.data/data/my_data/data_file
gcputils/__init__.py
gcputils/bq_client.py
gcputils/utils/__init__.py
gcputils/utils/bigquery_utils.py
gcputils/utils/common_utils.py
gcp_utility-2.0.5.dist-info/LICENSE.txt
gcp_utility-2.0.5.dist-info/METADATA
gcp_utility-2.0.5.dist-info/WHEEL
gcp_utility-2.0.5.dist-info/entry_points.txt
gcp_utility-2.0.5.dist-info/top_level.txt
gcp_utility-2.0.5.dist-info/RECORD
