Metadata-Version: 2.1
Name: gcp-utility
Version: 2.0.5
Summary: GCP utility will give additional custom features over gcs
Home-page: https://github.com/pypa/sampleproject
Author: Manojkumar vadivel
Author-email: manojkumar.vsj@gmail.com
License: UNKNOWN
Project-URL: Bug Reports, https://github.com/pypa/sampleproject/issues
Project-URL: Funding, https://donate.pypi.org
Project-URL: Say Thanks!, http://saythanks.io/to/example
Project-URL: Source, https://github.com/pypa/sampleproject/
Keywords: sample setuptools development
Platform: UNKNOWN
Classifier: Development Status :: 3 - Alpha
Classifier: Intended Audience :: Developers
Classifier: Topic :: Software Development :: Build Tools
Classifier: License :: OSI Approved :: MIT License
Classifier: Programming Language :: Python :: 2
Classifier: Programming Language :: Python :: 2.7
Requires-Python: >=2.6,<3
Requires-Dist: google-cloud-bigquery (==1.24.0)
Requires-Dist: Jinja2 (==2.11.3)
Provides-Extra: dev
Requires-Dist: check-manifest ; extra == 'dev'
Provides-Extra: test
Requires-Dist: coverage ; extra == 'test'
